imagemangler/__init__.py
imagemangler/cli.py
imagemangler/core/__init__.py
imagemangler/core/mangler.py
imagemangler/core/utils.py
imagemangler-0.1.6.dist-info/METADATA
imagemangler-0.1.6.dist-info/WHEEL
imagemangler-0.1.6.dist-info/entry_points.txt
imagemangler-0.1.6.dist-info/RECORD
